grimoire/__init__.py
grimoire/core.py
grimoire/errors.py
grimoire/templates.py
grimoire/utils.py
grimoire_if-1.0.7.dist-info/LICENSE
grimoire_if-1.0.7.dist-info/METADATA
grimoire_if-1.0.7.dist-info/WHEEL
grimoire_if-1.0.7.dist-info/top_level.txt
grimoire_if-1.0.7.dist-info/RECORD
