Metadata-Version: 2.1
Name: grimoire-if
Version: 1.0.7
Summary: Static Interactive Fiction Generator
Home-page: https://github.com/scrussell24/grimoire
Author: Scott Russell
Author-email: me@scottrussell.net
License: UNKNOWN
Platform: UNKNOWN
Classifier: Programming Language :: Python :: 3
Classifier: License :: OSI Approved :: MIT License
Classifier: Operating System :: OS Independent
Requires-Python: >=3.6
Requires-Dist: hype-html
